material_joapuiib/__init__.py
material_joapuiib/requirements.txt
material_joapuiib/extensions/collapse_code.py
material_joapuiib/extensions/emoji.py
material_joapuiib/plugins/__init__.py
material_joapuiib/plugins/badges.py
material_joapuiib/plugins/enviorment.py
material_joapuiib/plugins/filters.py
material_joapuiib/plugins/functions.py
material_joapuiib/plugins/sectionicons.py
material_joapuiib/templates/__init__.py
material_joapuiib/templates/document-base.html
material_joapuiib/templates/document.html
material_joapuiib/templates/exam.html
material_joapuiib/templates/main.html
material_joapuiib/templates/mkdocs_theme.yml
material_joapuiib/templates/programacio-base.html
material_joapuiib/templates/programacio.html
material_joapuiib/templates/slides.html
material_joapuiib/templates/theme-base.html
material_joapuiib/templates/.icons/artificial-intelligence-outline.svg
material_joapuiib/templates/.icons/artificial-intelligence.svg
material_joapuiib/templates/.icons/speedometer.svg
material_joapuiib/templates/.icons/intellij/breakpoint.svg
material_joapuiib/templates/.icons/intellij/class-abstract.svg
material_joapuiib/templates/.icons/intellij/class-junit-test.svg
material_joapuiib/templates/.icons/intellij/class.svg
material_joapuiib/templates/.icons/intellij/debug.svg
material_joapuiib/templates/.icons/intellij/enum.svg
material_joapuiib/templates/.icons/intellij/exception.svg
material_joapuiib/templates/.icons/intellij/exclude-folder.svg
material_joapuiib/templates/.icons/intellij/interface.svg
material_joapuiib/templates/.icons/intellij/maven-load.svg
material_joapuiib/templates/.icons/intellij/maven.svg
material_joapuiib/templates/.icons/intellij/package.svg
material_joapuiib/templates/.icons/intellij/record.svg
material_joapuiib/templates/.icons/intellij/resources-folder.svg
material_joapuiib/templates/.icons/intellij/resume.svg
material_joapuiib/templates/.icons/intellij/run.svg
material_joapuiib/templates/.icons/intellij/src-folder.svg
mkdocs_material_joapuiib-2.2.2.dist-info/METADATA
mkdocs_material_joapuiib-2.2.2.dist-info/WHEEL
mkdocs_material_joapuiib-2.2.2.dist-info/entry_points.txt
mkdocs_material_joapuiib-2.2.2.dist-info/top_level.txt
mkdocs_material_joapuiib-2.2.2.dist-info/RECORD
