Metadata-Version: 2.4
Name: mkdocs-material-joapuiib
Version: 2.2.2
Summary: Custom theme for MkDocs
Author-email: Joan Puigcerver <joapuiib@gmail.com>
Maintainer-email: Joan Puigcerver <joapuiib@gmail.com>
Project-URL: Repository, https://github.com/joapuiib/mkdocs-material-joapuiib
Requires-Python: >=3.5
Requires-Dist: markdown-captions~=2.1
Requires-Dist: markdown_grid_tables~=0.3
Requires-Dist: mkdocs~=1.6
Requires-Dist: mkdocs-alias-plugin~=0.8
Requires-Dist: mkdocs-awesome-nav~=3.0
Requires-Dist: mkdocs-drawio~=1.7
Requires-Dist: mkdocs-exclude-search~=0.6
Requires-Dist: mkdocs-git-revision-date-localized-plugin~=1.2
Requires-Dist: mkdocs-glightbox~=0.4
Requires-Dist: mkdocs-macros-plugin~=1.2
Requires-Dist: mkdocs-material~=9.7
Requires-Dist: mkdocs-static-i18n~=1.2
Requires-Dist: pygments-shell-console~=0.8
Requires-Dist: pymdown-extensions~=10.12
Requires-Dist: pymdown-rubric-extension~=0.1
Requires-Dist: pymdownx-inline-blocks~=0.1
Requires-Dist: unidecode~=1.3
Requires-Dist: markdown-span-attr
